.long-description.html
README.txt
setup.py
docs/CREDITS.txt
docs/HISTORY.txt
docs/INSTALL.txt
src/collective/__init__.py
src/collective.pfg.showrequest.egg-info/PKG-INFO
src/collective.pfg.showrequest.egg-info/SOURCES.txt
src/collective.pfg.showrequest.egg-info/dependency_links.txt
src/collective.pfg.showrequest.egg-info/entry_points.txt
src/collective.pfg.showrequest.egg-info/namespace_packages.txt
src/collective.pfg.showrequest.egg-info/not-zip-safe
src/collective.pfg.showrequest.egg-info/requires.txt
src/collective.pfg.showrequest.egg-info/top_level.txt
src/collective/pfg/__init__.py
src/collective/pfg/showrequest/__init__.py
src/collective/pfg/showrequest/configure.zcml
src/collective/pfg/showrequest/browser/__init__.py
src/collective/pfg/showrequest/browser/configure.zcml
src/collective/pfg/showrequest/browser/miscellaneous.py
src/collective/pfg/showrequest/browser/viewlet.py
src/collective/pfg/showrequest/browser/templates/edit_show_request.pt
src/collective/pfg/showrequest/browser/viewlets/setting.pt
src/collective/pfg/showrequest/browser/viewlets/show_request.pt
src/collective/pfg/showrequest/interfaces/__init__.py
src/collective/pfg/showrequest/interfaces/marker.py
src/collective/pfg/showrequest/interfaces/viewlet_manager.py
src/collective/pfg/showrequest/profiles/default/actions.xml
src/collective/pfg/showrequest/profiles/default/metadata.xml
src/collective/pfg/showrequest/tests/__init__.py
src/collective/pfg/showrequest/tests/base.py
src/collective/pfg/showrequest/tests/test_functional.py
src/collective/pfg/showrequest/tests/test_setup.py
src/collective/pfg/showrequest/tests/test_unittest.py
src/collective/pfg/showrequest/tests/functional/functional.txt
src/collective/pfg/showrequest/tests/unittest/browser.txt