Metadata-Version: 1.1
Name: collective.pfg.showrequest
Version: 0.5
Summary: Show previous form input values in viewlet for PloneFormGen.
Home-page: https://github.com/taito/collective.pfg.showrequest
Author: Taito Horiuchi
Author-email: taito.horiuchi@gmail.com
License: BSD
Platform: UNKNOWN
Classifier: Framework :: Plone
Classifier: Framework :: Plone :: 4.2
Classifier: License :: OSI Approved :: BSD License
Classifier: Programming Language :: Python
Classifier: Programming Language :: Python :: 2.7
